[
  {
    "id": "hhhyyy001",
    "name": "HOODIE «EMPTINESS OF THE SOUL» VOL.01",
    "imageUrl": "./img/hoody-kaneki/mockup.png",
    "imageBackUrl": "./img/hoody-kaneki/mockupBack.jpg",
    "printDesign": "./img/..",
    "substrateUrl": "./img/licoricewhite.png",
    "priceDrop": "4300",
    "pricePreorder": "3800",
    "salePrice": "0",
    "saleDate": "дата окончания акции",
    "dropDate": "2021-07-30",
    "barker": "для тех, кто знает сколько будет 1000 - 7",
    "clothes": "hoodie",
    "anime": "tokyo ghoul",
    "text": "Испоьлзуется оверсайз крой, с нашивками из джинсы и прямой полноцветной печатью.",
    "info": [
      "Оверсайз крой",
      {"Размеры:": ["М", "L", "XL"]},
      "Плотность: 350 гр / м"
    ],
    "feetback": [
      {
        "img": ["./img/lykbyk/hoody-kaneki/7.jpg"],
        "name": "Мокап",
        "userLink": "https://vk.com/iddizzycrow1947",
        "text": "Используется оверсайз крой, с нашивками из джинсы и прямой полноцветной печатью."
      },
      {
        "img": ["./img/lykbyk/hoody-kaneki/2.jpg"],
        "name": "Полина Малышева",
        "userLink": "https://vk.com/p.malysheva99",
        "text": "Фотомодель. Худи ей очень понравился"
      },
      {
        "img": ["./img/lykbyk/hoody-kaneki/3.jpg"],
        "name": "Данила Булгаков",
        "userLink": "https://vk.com/yrlywww",
        "text": "Фотомодель. Ему очень понравилось качество худи"
      },
      {
        "img": ["./img/lykbyk/hoody-kaneki/4.jpg"],
        "name": "Вячеслав Дядичко",
        "userLink": "https://vk.com/dead_666x7",
        "text": "Победитель нашего первого конкурса!"
      },
      {
        "img": ["./img/lykbyk/hoody-kaneki/5.jpg"],
        "name": "Даня Леоненко",
        "userLink": "https://vk.com/trap_alligator",
        "text": "ХУДАК СУПЕР КЛАСС!!!!. ЗАКАЗЫВАЙТЕ ОПТОМ ДЛЯ ВСЕЙ СЕМЬИ И ЖДИТЕ ЛОНГ. МАТЕРИАЛ ИМБА. КОГДА НАДЕВАЕШЬ ИГРАЕТ ПЕСНЯ ЛЕЛЕЛЕМИДАЙ. 1000-7?☠."
      },
      {
        "img": ["./img/lykbyk/hoody-kaneki/8.jpg"],
        "name": "Кирилл Иванов",
        "userLink": "https://vk.com/plvgboi",
        "text": "Худи лучшего качества, всем советую этот бренд. Ребята, вы лучшие, продолжайте в том же духе)"
      },
      {
        "img": ["./img/lykbyk/hoody-kaneki/9.jpg"],
        "name": "Ника Домбровская",
        "userLink": "https://vk.com/mbnikizzz",
        "text": "Хочу поблагодарить создателей сия прекрасного шедевра, чувствую себя максимально dead inside 🥵. Материал очень приятный, а принт просто невероятный 😍. Раскупайте, пока есть в ассортименте, не пожалеете)"
      },
      {
        "img": ["./img/lykbyk/hoody-kaneki/10.jpg"],
        "name": "Андрей Маслов",
        "userLink": "https://vk.com/andy.msl666",
        "text": "1000-7 \n Худак хорошего качества 🔥"
      },
      {
        "img": ["./img/lykbyk/hoody-kaneki/11.jpg"],
        "name": "Тигран Овакимян",
        "userLink": "https://vk.com/iddizzycrow1947",
        "text": "Знакомьтесь, это админ :)"
      },
      {
        "img": ["./img/lykbyk/hoody-kaneki/1.jpg"],
        "name": "Фотосессия",
        "userLink": "",
        "text": "Lorem ipsum dolor sit amet, consectetur adipisicing elit. Consequuntur, tempore voluptatem."
      }
    ]
  },
  {
      "id": "hhhyyy002",
      "name": "LONGSLIV «ГЛАЗА что то там» VOL.02",
      "imageUrl": "./img/hoody-kaneki/mockup.png",
      "imageBackUrl": "./img/hoody-kaneki/mockupBack.jpg",
      "substrateUrl": "./img/licoricewhite.png",
      "priceDrop": "2800",
      "pricePreorder": "2500",
      "dropDate": "2021-05-30",
      "anime": "tokyo ghoul",
      "text": "Используются разные виды такани. Рукава сделаны в стиле тай - дай",
      "info": [
        "Оверсайз крой",
        "Размеры: М / L / XL",
        "Плотность:  гр / м",
        "Двойные рукава"
      ]
    }
]
